harmony_client/__init__.py
harmony_client/logging_table.py
harmony_client/harmony_client.pyi
harmony_client/file_storage.py
harmony_client/harmony_client.cpython-312-x86_64-linux-gnu.so
harmony_client/py.typed
harmony_client/artifacts/custom_artifact.py
harmony_client/artifacts/__init__.py
harmony_client/artifacts/model_artifact.py
harmony_client/artifacts/dataset_artifact.py
harmony_client/internal/__init__.py
harmony_client/internal/utils.py
harmony_client/internal/eval_samples_html.py
harmony_client/runtime/data.py
harmony_client/runtime/__init__.py
harmony_client/runtime/decorators.py
harmony_client/runtime/runner.py
harmony_client/runtime/simple_notifier.py
harmony_client/runtime/model_artifact_save.py
harmony_client/runtime/context.py
harmony_client/runtime/dto/AdaptiveDataset.py
harmony_client/runtime/dto/__init__.py
harmony_client/runtime/dto/AdaptiveModel.py
harmony_client/runtime/dto/base.py
harmony_client/runtime/dto/AdaptiveGrader.py
harmony_client/runtime/dto/DatasetSampleFormats.py
harmony_client/parameters/__init__.py
harmony_client/parameters/model_kinds.py
harmony_client/parameters/dataset_kinds.py
harmony_client-0.1.0.dist-info/METADATA
harmony_client-0.1.0.dist-info/WHEEL
harmony_client-0.1.0.dist-info/RECORD
