Metadata-Version: 2.4
Name: harmony-client
Version: 0.1.0
Classifier: Programming Language :: Rust
Classifier: Programming Language :: Python :: 3.12
Classifier: Programming Language :: Python :: 3.13
Classifier: Programming Language :: Python :: Implementation :: CPython
Classifier: Programming Language :: Python :: Implementation :: PyPy
Requires-Dist: rich>=13.7.0
Requires-Dist: datasets>=2.14.0
Requires-Dist: hf-xet>=1.1.2
Requires-Dist: loguru>=0.7.2
Requires-Dist: pydantic-settings>=2.9.1
Requires-Dist: pydantic>=2.10.5
Requires-Dist: pybars3>=0.9.7
Requires-Dist: pysbd>=0.3.4
Requires-Dist: websockets>=15.0.1
Requires-Dist: setproctitle>=1.3.3
Requires-Dist: pydantic-xml>=2.16.0
Requires-Dist: openai>=1.42.0
Requires-Dist: pillow>=11.3.0
Requires-Dist: boto3>=1.40
Requires-Dist: tomli>=2
Requires-Dist: aiofiles>=25.1.0
Requires-Dist: tensorboardx>=2.6.2.2 ; extra == 'all-monitoring'
Requires-Dist: mlflow>=3.4.0 ; extra == 'all-monitoring'
Requires-Dist: wandb>=0.19.11 ; extra == 'all-monitoring'
Requires-Dist: mlflow>=3.4.0 ; extra == 'mlflow'
Requires-Dist: mlflow-skinny>=3.4.0 ; extra == 'mlflow-skinny'
Requires-Dist: tensorboardx>=2.6.2.2 ; extra == 'tensorboard'
Requires-Dist: wandb>=0.19.11 ; extra == 'wandb'
Provides-Extra: all_monitoring
Provides-Extra: mlflow
Provides-Extra: mlflow_skinny
Provides-Extra: tensorboard
Provides-Extra: wandb
Summary: Python client for Adaptive Harmony, with Rust-powered RPC communication
Requires-Python: >=3.12
